desyrdl/DesyListener.py
desyrdl/__init__.py
desyrdl/__main__.py
desyrdl/desyrdl.py
desyrdl/rdlformatcode.py
desyrdl/libraries/rdl/00_desyrdl_properties.rdl
desyrdl/libraries/rdl/10_generic_ibus.rdl
desyrdl/libraries/vhdl/axi4l_to_ibus.vhd
desyrdl/libraries/vhdl/ibus_to_axi4l.vhd
desyrdl/libraries/vhdl/include.txt
desyrdl/libraries/vhdl/pkg_desyrdl_common.vhd
desyrdl/templates/adoc/addrmap.adoc.jinja2
desyrdl/templates/adoc/include.txt
desyrdl/templates/cocotb/__init__.py
desyrdl/templates/cocotb/addrmap.py.jinja2
desyrdl/templates/cocotb/include.txt
desyrdl/templates/h/header.h.jinja2
desyrdl/templates/h/include.txt
desyrdl/templates/map/include.txt
desyrdl/templates/map/mapfile.mapp.jinja2
desyrdl/templates/map/mapfile.mapt.jinja2
desyrdl/templates/tcl/fwk_desyrdl_multi_lib.tcl.jinja2
desyrdl/templates/tcl/fwk_desyrdl_one_lib.tcl.jinja2
desyrdl/templates/tcl/include.txt
desyrdl/templates/tcl/vivado_desyrdl_multi_lib.tcl.jinja2
desyrdl/templates/tcl/vivado_desyrdl_one_lib.tcl.jinja2
desyrdl/templates/vhdl/decoder_axi4l.vhd.in
desyrdl/templates/vhdl/decoder_ibus.vhd.in
desyrdl/templates/vhdl/include.txt
desyrdl/templates/vhdl/pkg.vhd.in
desyrdl/templates/vhdl/top.vhd.in
desyrdl-1.4.1.dist-info/METADATA
desyrdl-1.4.1.dist-info/WHEEL
desyrdl-1.4.1.dist-info/entry_points.txt
desyrdl-1.4.1.dist-info/licenses/LICENSE
desyrdl-1.4.1.dist-info/RECORD
