Metadata-Version: 2.4
Name: desyrdl
Version: 1.4.1
Summary: DesyRDL - Tool for address space and register generation
Project-URL: Homepage, https://gitlab.desy.de/fpgafw/tools/desyrdl
Project-URL: Issues, https://gitlab.desy.de/fpgafw/tools/desyrdl/-/issues
Project-URL: Source, https://gitlab.desy.de/fpgafw/tools/desyrdl
Project-URL: Changelog, https://gitlab.desy.de/fpgafw/tools/desyrdl/blob/main/CHANGELOG.adoc
Author-email: MSK DESY <msk-firmware@desy.de>, Michael Büchler <michael.buechler@desy.de>, Lukasz Butkowski <lukasz.butkowski@desy.de>
Maintainer-email: Michael Büchler <michael.buechler@desy.de>, Lukasz Butkowski <lukasz.butkowski@desy.de>
License: Apache-2.0
License-File: LICENSE
Keywords: EDA,FPGA,SystemRDL
Classifier: Development Status :: 5 - Production/Stable
Classifier: License :: OSI Approved :: Apache Software License
Classifier: Operating System :: OS Independent
Classifier: Programming Language :: Python :: 3 :: Only
Classifier: Programming Language :: Python :: 3.8
Classifier: Programming Language :: Python :: 3.9
Classifier: Programming Language :: Python :: 3.10
Classifier: Programming Language :: Python :: 3.11
Classifier: Topic :: Scientific/Engineering :: Electronic Design Automation (EDA)
Requires-Python: >=3.8
Requires-Dist: jinja2>=3.0
Requires-Dist: systemrdl-compiler>=1.25
